[
{"SuperFunction": "rebuild",
  "Skip": [],
  "Be": true},
{"TowerPlaceCost":325,"TowerPlaced":"Slammer","TowerVector":"-271.4503173828125, 1.98369562625885, -399.9326477050781","Rotation":"0","TowerA1":"1716.5078358300962"},
{"TowerPlaceCost":325,"TowerPlaced":"Slammer","TowerVector":"-268.9203186035156, 1.1850886344909668, -397.2942810058594","Rotation":"0","TowerA1":"1718.8769412310794"},
{"TowerPlaceCost":325,"TowerPlaced":"Slammer","TowerVector":"-269.5646667480469, 1.185089111328125, -408.3114318847656","Rotation":"0","TowerA1":"1721.1411281791516"},
{"TowerPlaceCost":325,"TowerPlaced":"Slammer","TowerVector":"-266.301513671875, 1.185089111328125, -408.3611755371094","Rotation":"0","TowerA1":"1723.9075999371707"},
{"TargetWanted":4,"TargetWave":"WAVE 0","TowerTargetChange":-269.5646667480469,"TargetChangedAt":7},
{"TargetWanted":3,"TargetWave":"WAVE 0","TowerTargetChange":-269.5646667480469,"TargetChangedAt":7},
{"TargetWanted":2,"TargetWave":"WAVE 0","TowerTargetChange":-269.5646667480469,"TargetChangedAt":7},
{"TargetWanted":4,"TargetWave":"WAVE 0","TowerTargetChange":-266.301513671875,"TargetChangedAt":6},
{"TargetWanted":3,"TargetWave":"WAVE 0","TowerTargetChange":-266.301513671875,"TargetChangedAt":6},
{"TargetWanted":2,"TargetWave":"WAVE 0","TowerTargetChange":-266.301513671875,"TargetChangedAt":6},
{"TargetWanted":4,"TargetWave":"WAVE 0","TowerTargetChange":-271.4503173828125,"TargetChangedAt":5},
{"TargetWanted":3,"TargetWave":"WAVE 0","TowerTargetChange":-271.4503173828125,"TargetChangedAt":5},
{"TargetWanted":2,"TargetWave":"WAVE 0","TowerTargetChange":-271.4503173828125,"TargetChangedAt":5},
{"TargetWanted":4,"TargetWave":"WAVE 0","TowerTargetChange":-268.9203186035156,"TargetChangedAt":4},
{"TargetWanted":3,"TargetWave":"WAVE 0","TowerTargetChange":-268.9203186035156,"TargetChangedAt":4},
{"TargetWanted":2,"TargetWave":"WAVE 0","TowerTargetChange":-268.9203186035156,"TargetChangedAt":4},
{"SkipWhen":4,"SkipWave":"WAVE 1"},
{"SkipWhen":4,"SkipWave":"WAVE 2"},
{"TowerPlaceCost":3000,"TowerPlaced":"Combat Drone","TowerVector":"-256.5158386230469, 1.185089111328125, -402.55072021484375","Rotation":"0","TowerA1":"1785.7406039601192"},
{"TowerUpgraded":-256.5158386230469,"UpgradeCost":0,"UpgradePath":2},
{"TowerUpgraded":-256.5158386230469,"UpgradeCost":0,"UpgradePath":2},
{"TowerUpgraded":-256.5158386230469,"UpgradeCost":0,"UpgradePath":1},
{"TowerUpgraded":-269.5646667480469,"UpgradeCost":0,"UpgradePath":1},
{"TowerUpgraded":-269.5646667480469,"UpgradeCost":0,"UpgradePath":1},
{"TowerUpgraded":-269.5646667480469,"UpgradeCost":0,"UpgradePath":1},
{"TowerUpgraded":-269.5646667480469,"UpgradeCost":0,"UpgradePath":2},
{"TowerUpgraded":-269.5646667480469,"UpgradeCost":0,"UpgradePath":2},
{"TowerUpgraded":-266.301513671875,"UpgradeCost":0,"UpgradePath":1},
{"TowerUpgraded":-266.301513671875,"UpgradeCost":0,"UpgradePath":1},
{"TowerUpgraded":-266.301513671875,"UpgradeCost":0,"UpgradePath":1},
{"TowerUpgraded":-266.301513671875,"UpgradeCost":0,"UpgradePath":2},
{"TowerUpgraded":-266.301513671875,"UpgradeCost":0,"UpgradePath":2},
{"TowerUpgraded":-271.4503173828125,"UpgradeCost":0,"UpgradePath":1},
{"TowerUpgraded":-271.4503173828125,"UpgradeCost":0,"UpgradePath":1},
{"TowerUpgraded":-271.4503173828125,"UpgradeCost":0,"UpgradePath":1},
{"TowerUpgraded":-271.4503173828125,"UpgradeCost":0,"UpgradePath":2},
{"TowerUpgraded":-271.4503173828125,"UpgradeCost":0,"UpgradePath":2},
{"TowerUpgraded":-268.9203186035156,"UpgradeCost":0,"UpgradePath":1},
{"TowerUpgraded":-268.9203186035156,"UpgradeCost":0,"UpgradePath":1},
{"TowerUpgraded":-268.9203186035156,"UpgradeCost":0,"UpgradePath":1},
{"TowerUpgraded":-268.9203186035156,"UpgradeCost":0,"UpgradePath":2},
{"TowerUpgraded":-268.9203186035156,"UpgradeCost":0,"UpgradePath":2},
{"TowerUpgraded":-271.4503173828125,"UpgradeCost":0,"UpgradePath":1},
{"TowerUpgraded":-269.5646667480469,"UpgradeCost":0,"UpgradePath":1},
{"TowerUpgraded":-266.301513671875,"UpgradeCost":0,"UpgradePath":1},
{"TowerUpgraded":-268.9203186035156,"UpgradeCost":0,"UpgradePath":1},
{"TowerUpgraded":-256.5158386230469,"UpgradeCost":0,"UpgradePath":2},
{"TowerUpgraded":-256.5158386230469,"UpgradeCost":0,"UpgradePath":1},
{"TowerPlaceCost":900,"TowerPlaced":"Golden Ranger","TowerVector":"-251.68539428710938, 1.1828293800354004, -401.46624755859375","Rotation":"0","TowerA1":"1960.1498845862225"},
{"TowerUpgraded":-251.68539428710938,"UpgradeCost":0,"UpgradePath":2},
{"TowerUpgraded":-251.68539428710938,"UpgradeCost":0,"UpgradePath":2},
{"TowerUpgraded":-251.68539428710938,"UpgradeCost":0,"UpgradePath":2},
{"TowerUpgraded":-251.68539428710938,"UpgradeCost":0,"UpgradePath":2},
{"TowerUpgraded":-251.68539428710938,"UpgradeCost":0,"UpgradePath":1},
{"TowerUpgraded":-251.68539428710938,"UpgradeCost":0,"UpgradePath":1},
{"TowerUpgraded":-271.4503173828125,"UpgradeCost":0,"UpgradePath":1},
{"TowerUpgraded":-269.5646667480469,"UpgradeCost":0,"UpgradePath":1},
{"TowerUpgraded":-266.301513671875,"UpgradeCost":0,"UpgradePath":1},
{"TowerUpgraded":-268.9203186035156,"UpgradeCost":0,"UpgradePath":1},
{"TowerPlaceCost":2450,"TowerPlaced":"EDJ","TowerVector":"-254.9563751220703, 1.1850895881652832, -401.7395935058594","Rotation":"0","TowerA1":"2048.9480328960344"},
{"TowerUpgraded":-254.9563751220703,"UpgradeCost":0,"UpgradePath":1},
{"TowerUpgraded":-254.9563751220703,"UpgradeCost":0,"UpgradePath":1},
{"TowerUpgraded":-254.9563751220703,"UpgradeCost":0,"UpgradePath":1},
{"TowerUpgraded":-254.9563751220703,"UpgradeCost":0,"UpgradePath":1},
{"TowerUpgraded":-254.9563751220703,"UpgradeCost":0,"UpgradePath":1},
{"TowerUpgraded":-254.9563751220703,"UpgradeCost":0,"UpgradePath":2},
{"TowerUpgraded":-254.9563751220703,"UpgradeCost":0,"UpgradePath":2},
{"TowerPlaceCost":2450,"TowerPlaced":"EDJ","TowerVector":"-255.00682067871094, 1.185089111328125, -405.25189208984375","Rotation":"0","TowerA1":"2055.56913721608"},
{"TowerUpgraded":-255.00682067871095,"UpgradeCost":0,"UpgradePath":2},
{"TowerUpgraded":-255.00682067871095,"UpgradeCost":0,"UpgradePath":2},
{"TowerUpgraded":-255.00682067871095,"UpgradeCost":0,"UpgradePath":2},
{"TowerUpgraded":-255.00682067871095,"UpgradeCost":0,"UpgradePath":2},
{"TowerUpgraded":-255.00682067871095,"UpgradeCost":0,"UpgradePath":1},
{"TowerUpgraded":-255.00682067871095,"UpgradeCost":0,"UpgradePath":1},
{"TowerUpgraded":-255.00682067871095,"UpgradeCost":0,"UpgradePath":2},
{"TowerUpgraded":-251.68539428710938,"UpgradeCost":0,"UpgradePath":2},
{"TowerPlaceCost":225,"TowerPlaced":"Cryo Blaster","TowerVector":"-261.51116943359375, 1.185089111328125, -401.5632629394531","Rotation":"0","TowerA1":"2081.60305881314"},
{"TowerUpgraded":-261.51116943359377,"UpgradeCost":0,"UpgradePath":2},
{"TowerUpgraded":-261.51116943359377,"UpgradeCost":0,"UpgradePath":2},
{"TowerUpgraded":-261.51116943359377,"UpgradeCost":0,"UpgradePath":1},
{"TowerUpgraded":-261.51116943359377,"UpgradeCost":0,"UpgradePath":1},
{"TowerUpgraded":-261.51116943359377,"UpgradeCost":0,"UpgradePath":1},
{"TowerUpgraded":-261.51116943359377,"UpgradeCost":0,"UpgradePath":1},
{"TowerUpgraded":-261.51116943359377,"UpgradeCost":0,"UpgradePath":1},
{"TowerPlaceCost":225,"TowerPlaced":"Cryo Blaster","TowerVector":"-261.2357482910156, 1.185089111328125, -404.70245361328125","Rotation":"0","TowerA1":"2086.718315516133"},
{"TowerUpgraded":-261.2357482910156,"UpgradeCost":0,"UpgradePath":1},
{"TowerUpgraded":-261.2357482910156,"UpgradeCost":0,"UpgradePath":1},
{"TowerUpgraded":-261.2357482910156,"UpgradeCost":0,"UpgradePath":1},
{"TowerUpgraded":-261.2357482910156,"UpgradeCost":0,"UpgradePath":1},
{"TowerUpgraded":-261.2357482910156,"UpgradeCost":0,"UpgradePath":1},
{"TowerUpgraded":-261.2357482910156,"UpgradeCost":0,"UpgradePath":2},
{"TowerUpgraded":-261.2357482910156,"UpgradeCost":0,"UpgradePath":2},
{"TowerPlaceCost":225,"TowerPlaced":"Cryo Blaster","TowerVector":"-261.72528076171875, 1.185089111328125, -407.6674499511719","Rotation":"0","TowerA1":"2090.1324279811233"},
{"TowerUpgraded":-261.72528076171877,"UpgradeCost":0,"UpgradePath":1},
{"TowerUpgraded":-261.72528076171877,"UpgradeCost":0,"UpgradePath":1},
{"TowerUpgraded":-261.72528076171877,"UpgradeCost":0,"UpgradePath":1},
{"TowerUpgraded":-261.72528076171877,"UpgradeCost":0,"UpgradePath":1},
{"TowerUpgraded":-261.72528076171877,"UpgradeCost":0,"UpgradePath":1},
{"TowerUpgraded":-261.72528076171877,"UpgradeCost":0,"UpgradePath":2},
{"TowerUpgraded":-261.72528076171877,"UpgradeCost":0,"UpgradePath":2},
{"TowerPlaceCost":225,"TowerPlaced":"Cryo Blaster","TowerVector":"-258.40106201171875, 1.185089111328125, -401.6307067871094","Rotation":"0","TowerA1":"2095.5908381622285"},
{"TowerUpgraded":-258.40106201171877,"UpgradeCost":0,"UpgradePath":1},
{"TowerUpgraded":-258.40106201171877,"UpgradeCost":0,"UpgradePath":1},
{"TowerUpgraded":-258.40106201171877,"UpgradeCost":0,"UpgradePath":2},
{"TowerUpgraded":-258.40106201171877,"UpgradeCost":0,"UpgradePath":2},
{"TowerUpgraded":-258.40106201171877,"UpgradeCost":0,"UpgradePath":2},
{"TowerUpgraded":-258.40106201171877,"UpgradeCost":0,"UpgradePath":2},
{"TowerUpgraded":-258.40106201171877,"UpgradeCost":0,"UpgradePath":2},
{"TowerPlaceCost":225,"TowerPlaced":"Cryo Blaster","TowerVector":"-258.43426513671875, 1.1850895881652832, -406.0537109375","Rotation":"0","TowerA1":"2102.4033916969784"},
{"TowerUpgraded":-258.43426513671877,"UpgradeCost":0,"UpgradePath":2},
{"TowerUpgraded":-258.43426513671877,"UpgradeCost":0,"UpgradePath":2},
{"TowerUpgraded":-258.43426513671877,"UpgradeCost":0,"UpgradePath":2},
{"TowerUpgraded":-258.43426513671877,"UpgradeCost":0,"UpgradePath":2},
{"TowerUpgraded":-258.43426513671877,"UpgradeCost":0,"UpgradePath":2},
{"TowerUpgraded":-258.43426513671877,"UpgradeCost":0,"UpgradePath":1},
{"TowerUpgraded":-258.43426513671877,"UpgradeCost":0,"UpgradePath":1},
{"TowerPlaceCost":225,"TowerPlaced":"Cryo Blaster","TowerVector":"-251.233154296875, 1.1828293800354004, -404.560302734375","Rotation":"0","TowerA1":"2108.123193996027"},
{"TowerUpgraded":-251.233154296875,"UpgradeCost":0,"UpgradePath":2},
{"TowerUpgraded":-251.233154296875,"UpgradeCost":0,"UpgradePath":2},
{"TowerUpgraded":-251.233154296875,"UpgradeCost":0,"UpgradePath":2},
{"TowerUpgraded":-251.233154296875,"UpgradeCost":0,"UpgradePath":2},
{"TowerUpgraded":-251.233154296875,"UpgradeCost":0,"UpgradePath":2},
{"TowerUpgraded":-251.233154296875,"UpgradeCost":0,"UpgradePath":1},
{"TowerUpgraded":-251.233154296875,"UpgradeCost":0,"UpgradePath":1},
{"TowerPlaceCost":225,"TowerPlaced":"Cryo Blaster","TowerVector":"-258.95556640625, 1.185089111328125, -409.2580871582031","Rotation":"0","TowerA1":"2113.35779367527"},
{"TowerUpgraded":-258.95556640625,"UpgradeCost":0,"UpgradePath":2},
{"TowerUpgraded":-258.95556640625,"UpgradeCost":0,"UpgradePath":2},
{"TowerUpgraded":-258.95556640625,"UpgradeCost":0,"UpgradePath":2},
{"TowerUpgraded":-258.95556640625,"UpgradeCost":0,"UpgradePath":2},
{"TowerUpgraded":-258.95556640625,"UpgradeCost":0,"UpgradePath":2},
{"TowerUpgraded":-258.95556640625,"UpgradeCost":0,"UpgradePath":1},
{"TowerUpgraded":-258.95556640625,"UpgradeCost":0,"UpgradePath":1},
{"TowerPlaceCost":225,"TowerPlaced":"Cryo Blaster","TowerVector":"-255.82965087890625, 1.185089111328125, -408.59893798828125","Rotation":"0","TowerA1":"2117.7598588042893"},
{"TowerUpgraded":-255.82965087890626,"UpgradeCost":0,"UpgradePath":2},
{"TowerUpgraded":-255.82965087890626,"UpgradeCost":0,"UpgradePath":2},
{"TowerUpgraded":-255.82965087890626,"UpgradeCost":0,"UpgradePath":2},
{"TowerUpgraded":-255.82965087890626,"UpgradeCost":0,"UpgradePath":2},
{"TowerUpgraded":-255.82965087890626,"UpgradeCost":0,"UpgradePath":2},
{"TowerUpgraded":-255.82965087890626,"UpgradeCost":0,"UpgradePath":1},
{"TowerUpgraded":-255.82965087890626,"UpgradeCost":0,"UpgradePath":1},
{"TowerPlaceCost":225,"TowerPlaced":"Cryo Blaster","TowerVector":"-252.72442626953125, 1.185089111328125, -407.8321228027344","Rotation":"0","TowerA1":"2120.9206199040636"},
{"TowerUpgraded":-252.72442626953126,"UpgradeCost":0,"UpgradePath":2},
{"TowerUpgraded":-252.72442626953126,"UpgradeCost":0,"UpgradePath":2},
{"TowerUpgraded":-252.72442626953126,"UpgradeCost":0,"UpgradePath":2},
{"TowerUpgraded":-252.72442626953126,"UpgradeCost":0,"UpgradePath":2},
{"TowerUpgraded":-252.72442626953126,"UpgradeCost":0,"UpgradePath":2},
{"TowerUpgraded":-252.72442626953126,"UpgradeCost":0,"UpgradePath":1},
{"TowerUpgraded":-252.72442626953126,"UpgradeCost":0,"UpgradePath":1},
{"TowerPlaceCost":225,"TowerPlaced":"Cryo Blaster","TowerVector":"-261.7476501464844, 1.1850895881652832, -410.7422180175781","Rotation":"0","TowerA1":"2126.080051705241"},
{"TowerUpgraded":-261.7476501464844,"UpgradeCost":0,"UpgradePath":2},
{"TowerUpgraded":-261.7476501464844,"UpgradeCost":0,"UpgradePath":2},
{"TowerUpgraded":-261.7476501464844,"UpgradeCost":0,"UpgradePath":2},
{"TowerUpgraded":-261.7476501464844,"UpgradeCost":0,"UpgradePath":2},
{"TowerUpgraded":-261.7476501464844,"UpgradeCost":0,"UpgradePath":2},
{"TowerUpgraded":-261.7476501464844,"UpgradeCost":0,"UpgradePath":1},
{"TowerUpgraded":-261.7476501464844,"UpgradeCost":0,"UpgradePath":1},
{"TowerPlaceCost":225,"TowerPlaced":"Cryo Blaster","TowerVector":"-264.7137756347656, 1.185089111328125, -411.240478515625","Rotation":"0","TowerA1":"2134.1777961989865"},
{"TowerUpgraded":-264.7137756347656,"UpgradeCost":0,"UpgradePath":2},
{"TowerUpgraded":-264.7137756347656,"UpgradeCost":0,"UpgradePath":2},
{"TowerUpgraded":-264.7137756347656,"UpgradeCost":0,"UpgradePath":2},
{"TowerUpgraded":-264.7137756347656,"UpgradeCost":0,"UpgradePath":2},
{"TowerUpgraded":-264.7137756347656,"UpgradeCost":0,"UpgradePath":2},
{"TowerUpgraded":-264.7137756347656,"UpgradeCost":0,"UpgradePath":1},
{"TowerUpgraded":-264.7137756347656,"UpgradeCost":0,"UpgradePath":1},
{"TowerUpgraded":-256.5158386230469,"UpgradeCost":0,"UpgradePath":2},
{"TowerUpgraded":-256.5158386230469,"UpgradeCost":0,"UpgradePath":2},
{"TowerPlaceCost":3000,"TowerPlaced":"Combat Drone","TowerVector":"-252.4580078125, 1.185089111328125, -411.6634216308594","Rotation":"0","TowerA1":"2160.9764177319594"},
{"TowerUpgraded":-252.4580078125,"UpgradeCost":0,"UpgradePath":2},
{"TowerUpgraded":-252.4580078125,"UpgradeCost":0,"UpgradePath":2},
{"TowerUpgraded":-252.4580078125,"UpgradeCost":0,"UpgradePath":2},
{"TowerUpgraded":-252.4580078125,"UpgradeCost":0,"UpgradePath":2},
{"TowerUpgraded":-252.4580078125,"UpgradeCost":0,"UpgradePath":2},
{"TowerUpgraded":-252.4580078125,"UpgradeCost":0,"UpgradePath":1},
{"TowerUpgraded":-252.4580078125,"UpgradeCost":0,"UpgradePath":1},
{"TowerPlaceCost":925,"TowerPlaced":"Toxicnator","TowerVector":"-267.8190002441406, 1.185089111328125, -411.1964416503906","Rotation":"0","TowerA1":"2174.2316818679683"},
{"TowerUpgraded":-267.8190002441406,"UpgradeCost":0,"UpgradePath":2},
{"TowerUpgraded":-267.8190002441406,"UpgradeCost":0,"UpgradePath":2},
{"TowerUpgraded":-267.8190002441406,"UpgradeCost":0,"UpgradePath":2},
{"TowerUpgraded":-267.8190002441406,"UpgradeCost":0,"UpgradePath":2},
{"TowerUpgraded":-267.8190002441406,"UpgradeCost":0,"UpgradePath":2},
{"TowerUpgraded":-267.8190002441406,"UpgradeCost":0,"UpgradePath":1},
{"TowerUpgraded":-267.8190002441406,"UpgradeCost":0,"UpgradePath":1},
{"TowerPlaceCost":925,"TowerPlaced":"Toxicnator","TowerVector":"-270.9493408203125, 1.1850895881652832, -410.99481201171875","Rotation":"0","TowerA1":"2187.659162821248"},
{"TowerUpgraded":-270.9493408203125,"UpgradeCost":0,"UpgradePath":2},
{"TowerUpgraded":-270.9493408203125,"UpgradeCost":0,"UpgradePath":2},
{"TowerUpgraded":-270.9493408203125,"UpgradeCost":0,"UpgradePath":2},
{"TowerUpgraded":-270.9493408203125,"UpgradeCost":0,"UpgradePath":2},
{"TowerUpgraded":-270.9493408203125,"UpgradeCost":0,"UpgradePath":2},
{"TowerUpgraded":-270.9493408203125,"UpgradeCost":0,"UpgradePath":1},
{"TowerUpgraded":-270.9493408203125,"UpgradeCost":0,"UpgradePath":1},
{"TowerPlaceCost":225,"TowerPlaced":"Cryo Blaster","TowerVector":"-262.89813232421875, 1.185089111328125, -414.0979919433594","Rotation":"0","TowerA1":"2212.9866200708784"},
{"TowerUpgraded":-262.89813232421877,"UpgradeCost":0,"UpgradePath":2},
{"TowerUpgraded":-262.89813232421877,"UpgradeCost":0,"UpgradePath":2},
{"TowerUpgraded":-262.89813232421877,"UpgradeCost":0,"UpgradePath":2},
{"TowerUpgraded":-262.89813232421877,"UpgradeCost":0,"UpgradePath":2},
{"TowerUpgraded":-262.89813232421877,"UpgradeCost":0,"UpgradePath":2},
{"TowerUpgraded":-262.89813232421877,"UpgradeCost":0,"UpgradePath":1},
{"TowerUpgraded":-262.89813232421877,"UpgradeCost":0,"UpgradePath":1},
{"TowerPlaceCost":225,"TowerPlaced":"Cryo Blaster","TowerVector":"-259.6296081542969, 1.185089111328125, -413.07012939453125","Rotation":"0","TowerA1":"2216.7811325159855"},
{"TowerUpgraded":-259.6296081542969,"UpgradeCost":0,"UpgradePath":2},
{"TowerUpgraded":-259.6296081542969,"UpgradeCost":0,"UpgradePath":2},
{"TowerUpgraded":-259.6296081542969,"UpgradeCost":0,"UpgradePath":2},
{"TowerUpgraded":-259.6296081542969,"UpgradeCost":0,"UpgradePath":2},
{"TowerUpgraded":-259.6296081542969,"UpgradeCost":0,"UpgradePath":2},
{"TowerUpgraded":-259.6296081542969,"UpgradeCost":0,"UpgradePath":1},
{"TowerUpgraded":-259.6296081542969,"UpgradeCost":0,"UpgradePath":1},
{"TowerPlaceCost":225,"TowerPlaced":"Cryo Blaster","TowerVector":"-256.4947204589844, 1.185089111328125, -411.6158447265625","Rotation":"0","TowerA1":"2220.2654833802953"},
{"TowerUpgraded":-256.4947204589844,"UpgradeCost":0,"UpgradePath":2},
{"TowerUpgraded":-256.4947204589844,"UpgradeCost":0,"UpgradePath":2},
{"TowerUpgraded":-256.4947204589844,"UpgradeCost":0,"UpgradePath":2},
{"TowerUpgraded":-256.4947204589844,"UpgradeCost":0,"UpgradePath":2},
{"TowerUpgraded":-256.4947204589844,"UpgradeCost":0,"UpgradePath":2},
{"TowerUpgraded":-256.4947204589844,"UpgradeCost":0,"UpgradePath":1},
{"TowerUpgraded":-256.4947204589844,"UpgradeCost":0,"UpgradePath":1},
{"TowerPlaceCost":225,"TowerPlaced":"Cryo Blaster","TowerVector":"-253.37489318847656, 1.1850886344909668, -411.34649658203125","Rotation":"0","TowerA1":"2224.3285140092485"},
{"TowerUpgraded":-253.37489318847657,"UpgradeCost":0,"UpgradePath":2},
{"TowerUpgraded":-253.37489318847657,"UpgradeCost":0,"UpgradePath":2},
{"TowerUpgraded":-253.37489318847657,"UpgradeCost":0,"UpgradePath":2},
{"TowerUpgraded":-253.37489318847657,"UpgradeCost":0,"UpgradePath":2},
{"TowerUpgraded":-253.37489318847657,"UpgradeCost":0,"UpgradePath":2},
{"TowerUpgraded":-253.37489318847657,"UpgradeCost":0,"UpgradePath":1},
{"TowerUpgraded":-253.37489318847657,"UpgradeCost":0,"UpgradePath":1},
{"TowerPlaceCost":225,"TowerPlaced":"Cryo Blaster","TowerVector":"-248.45579528808594, 1.1828293800354004, -401.6039123535156","Rotation":"0","TowerA1":"2229.8214147211984"},
{"TowerUpgraded":-248.45579528808595,"UpgradeCost":0,"UpgradePath":2},
{"TowerUpgraded":-248.45579528808595,"UpgradeCost":0,"UpgradePath":2},
{"TowerUpgraded":-248.45579528808595,"UpgradeCost":0,"UpgradePath":2},
{"TowerUpgraded":-248.45579528808595,"UpgradeCost":0,"UpgradePath":2},
{"TowerUpgraded":-248.45579528808595,"UpgradeCost":0,"UpgradePath":2},
{"TowerUpgraded":-248.45579528808595,"UpgradeCost":0,"UpgradePath":1},
{"TowerUpgraded":-248.45579528808595,"UpgradeCost":0,"UpgradePath":1},
{"TowerPlaceCost":225,"TowerPlaced":"Cryo Blaster","TowerVector":"-247.87322998046875, 1.1828293800354004, -404.72235107421875","Rotation":"0","TowerA1":"2234.3386537209153"},
{"TowerUpgraded":-247.87322998046876,"UpgradeCost":0,"UpgradePath":2},
{"TowerUpgraded":-247.87322998046876,"UpgradeCost":0,"UpgradePath":2},
{"TowerUpgraded":-247.87322998046876,"UpgradeCost":0,"UpgradePath":2},
{"TowerUpgraded":-247.87322998046876,"UpgradeCost":0,"UpgradePath":2},
{"TowerUpgraded":-247.87322998046876,"UpgradeCost":0,"UpgradePath":2},
{"TowerUpgraded":-247.87322998046876,"UpgradeCost":0,"UpgradePath":1},
{"TowerUpgraded":-247.87322998046876,"UpgradeCost":0,"UpgradePath":1},
{"TowerPlaceCost":225,"TowerPlaced":"Cryo Blaster","TowerVector":"-249.6744384765625, 1.1828293800354004, -407.6357727050781","Rotation":"0","TowerA1":"2237.9161031423137"},
{"TowerUpgraded":-249.6744384765625,"UpgradeCost":0,"UpgradePath":2},
{"TowerUpgraded":-249.6744384765625,"UpgradeCost":0,"UpgradePath":2},
{"TowerUpgraded":-249.6744384765625,"UpgradeCost":0,"UpgradePath":2},
{"TowerUpgraded":-249.6744384765625,"UpgradeCost":0,"UpgradePath":2},
{"TowerUpgraded":-249.6744384765625,"UpgradeCost":0,"UpgradePath":2},
{"TowerUpgraded":-249.6744384765625,"UpgradeCost":0,"UpgradePath":1},
{"TowerUpgraded":-249.6744384765625,"UpgradeCost":0,"UpgradePath":1},
{"TowerPlaceCost":225,"TowerPlaced":"Cryo Blaster","TowerVector":"-250.18099975585938, 1.1828293800354004, -410.6496276855469","Rotation":"0","TowerA1":"2243.977934278082"},
{"TowerUpgraded":-250.18099975585938,"UpgradeCost":0,"UpgradePath":2},
{"TowerUpgraded":-250.18099975585938,"UpgradeCost":0,"UpgradePath":2},
{"TowerUpgraded":-250.18099975585938,"UpgradeCost":0,"UpgradePath":2},
{"TowerUpgraded":-250.18099975585938,"UpgradeCost":0,"UpgradePath":2},
{"TowerUpgraded":-250.18099975585938,"UpgradeCost":0,"UpgradePath":2},
{"TowerUpgraded":-250.18099975585938,"UpgradeCost":0,"UpgradePath":1},
{"TowerUpgraded":-250.18099975585938,"UpgradeCost":0,"UpgradePath":1},
{"TowerPlaceCost":225,"TowerPlaced":"Cryo Blaster","TowerVector":"-257.1813049316406, 1.002092719078064, -414.8155822753906","Rotation":"0","TowerA1":"2248.9251319612376"},
{"TowerUpgraded":-257.1813049316406,"UpgradeCost":0,"UpgradePath":2},
{"TowerUpgraded":-257.1813049316406,"UpgradeCost":0,"UpgradePath":2},
{"TowerUpgraded":-257.1813049316406,"UpgradeCost":0,"UpgradePath":2},
{"TowerUpgraded":-257.1813049316406,"UpgradeCost":0,"UpgradePath":2},
{"TowerUpgraded":-257.1813049316406,"UpgradeCost":0,"UpgradePath":2},
{"TowerUpgraded":-257.1813049316406,"UpgradeCost":0,"UpgradePath":1},
{"TowerUpgraded":-257.1813049316406,"UpgradeCost":0,"UpgradePath":1},
{"TowerPlaceCost":225,"TowerPlaced":"Cryo Blaster","TowerVector":"-254.15309143066406, 1.1828293800354004, -414.2666015625","Rotation":"0","TowerA1":"2252.485061382875"},
{"TowerUpgraded":-254.15309143066407,"UpgradeCost":0,"UpgradePath":2},
{"TowerUpgraded":-254.15309143066407,"UpgradeCost":0,"UpgradePath":2},
{"TowerUpgraded":-254.15309143066407,"UpgradeCost":0,"UpgradePath":2},
{"TowerUpgraded":-254.15309143066407,"UpgradeCost":0,"UpgradePath":2},
{"TowerUpgraded":-254.15309143066407,"UpgradeCost":0,"UpgradePath":2},
{"TowerUpgraded":-254.15309143066407,"UpgradeCost":0,"UpgradePath":1},
{"TowerUpgraded":-254.15309143066407,"UpgradeCost":0,"UpgradePath":1},
{"TowerPlaceCost":225,"TowerPlaced":"Cryo Blaster","TowerVector":"-251.10716247558594, 1.1828293800354004, -413.5139465332031","Rotation":"0","TowerA1":"2265.2915562549606"},
{"TowerUpgraded":-251.10716247558595,"UpgradeCost":0,"UpgradePath":2},
{"TowerUpgraded":-251.10716247558595,"UpgradeCost":0,"UpgradePath":2},
{"TowerUpgraded":-251.10716247558595,"UpgradeCost":0,"UpgradePath":2},
{"TowerUpgraded":-251.10716247558595,"UpgradeCost":0,"UpgradePath":2},
{"TowerUpgraded":-251.10716247558595,"UpgradeCost":0,"UpgradePath":2},
{"TowerUpgraded":-251.10716247558595,"UpgradeCost":0,"UpgradePath":1},
{"TowerUpgraded":-251.10716247558595,"UpgradeCost":0,"UpgradePath":1},
{"TowerPlaceCost":225,"TowerPlaced":"Cryo Blaster","TowerVector":"-245.2617950439453, 1.1828293800354004, -401.29779052734375","Rotation":"0","TowerA1":"2269.7889990732074"},
{"TowerUpgraded":-245.2617950439453,"UpgradeCost":0,"UpgradePath":2},
{"TowerUpgraded":-245.2617950439453,"UpgradeCost":0,"UpgradePath":2},
{"TowerUpgraded":-245.2617950439453,"UpgradeCost":0,"UpgradePath":2},
{"TowerUpgraded":-245.2617950439453,"UpgradeCost":0,"UpgradePath":2},
{"TowerUpgraded":-245.2617950439453,"UpgradeCost":0,"UpgradePath":2},
{"TowerUpgraded":-245.2617950439453,"UpgradeCost":0,"UpgradePath":1},
{"TowerUpgraded":-245.2617950439453,"UpgradeCost":0,"UpgradePath":1},
{"TowerPlaceCost":225,"TowerPlaced":"Cryo Blaster","TowerVector":"-244.86390686035156, 1.1828293800354004, -404.5755615234375","Rotation":"0","TowerA1":"2274.4632145762444"},
{"TowerUpgraded":-244.86390686035157,"UpgradeCost":0,"UpgradePath":2},
{"TowerUpgraded":-244.86390686035157,"UpgradeCost":0,"UpgradePath":2},
{"TowerUpgraded":-244.86390686035157,"UpgradeCost":0,"UpgradePath":2},
{"TowerUpgraded":-244.86390686035157,"UpgradeCost":0,"UpgradePath":2},
{"TowerUpgraded":-244.86390686035157,"UpgradeCost":0,"UpgradePath":2},
{"TowerUpgraded":-244.86390686035157,"UpgradeCost":0,"UpgradePath":1},
{"TowerUpgraded":-244.86390686035157,"UpgradeCost":0,"UpgradePath":1},
{"TowerPlaceCost":225,"TowerPlaced":"Cryo Blaster","TowerVector":"-246.30955505371094, 1.1828293800354004, -407.4566955566406","Rotation":"0","TowerA1":"2278.501605270896"},
{"TowerUpgraded":-246.30955505371095,"UpgradeCost":0,"UpgradePath":2},
{"TowerUpgraded":-246.30955505371095,"UpgradeCost":0,"UpgradePath":2},
{"TowerUpgraded":-246.30955505371095,"UpgradeCost":0,"UpgradePath":2},
{"TowerUpgraded":-246.30955505371095,"UpgradeCost":0,"UpgradePath":2},
{"TowerUpgraded":-246.30955505371095,"UpgradeCost":0,"UpgradePath":2},
{"TowerUpgraded":-246.30955505371095,"UpgradeCost":0,"UpgradePath":1},
{"TowerUpgraded":-246.30955505371095,"UpgradeCost":0,"UpgradePath":1},
{"TowerPlaceCost":225,"TowerPlaced":"Cryo Blaster","TowerVector":"-247.06581115722656, 1.1828293800354004, -410.6400146484375","Rotation":"0","TowerA1":"2282.175404490903"},
{"TowerUpgraded":-247.06581115722657,"UpgradeCost":0,"UpgradePath":2},
{"TowerUpgraded":-247.06581115722657,"UpgradeCost":0,"UpgradePath":2},
{"TowerUpgraded":-247.06581115722657,"UpgradeCost":0,"UpgradePath":2},
{"TowerUpgraded":-247.06581115722657,"UpgradeCost":0,"UpgradePath":2},
{"TowerUpgraded":-247.06581115722657,"UpgradeCost":0,"UpgradePath":2},
{"TowerUpgraded":-247.06581115722657,"UpgradeCost":0,"UpgradePath":1},
{"TowerUpgraded":-247.06581115722657,"UpgradeCost":0,"UpgradePath":1},
{"TowerPlaceCost":225,"TowerPlaced":"Cryo Blaster","TowerVector":"-248.04168701171875, 1.1828293800354004, -413.95751953125","Rotation":"0","TowerA1":"2286.420592323877"},
{"TowerUpgraded":-248.04168701171876,"UpgradeCost":0,"UpgradePath":2},
{"TowerUpgraded":-248.04168701171876,"UpgradeCost":0,"UpgradePath":2},
{"TowerUpgraded":-248.04168701171876,"UpgradeCost":0,"UpgradePath":2},
{"TowerUpgraded":-248.04168701171876,"UpgradeCost":0,"UpgradePath":2},
{"TowerUpgraded":-248.04168701171876,"UpgradeCost":0,"UpgradePath":2},
{"TowerUpgraded":-248.04168701171876,"UpgradeCost":0,"UpgradePath":1},
{"TowerUpgraded":-248.04168701171876,"UpgradeCost":0,"UpgradePath":1},
{"TowerPlaceCost":925,"TowerPlaced":"Toxicnator","TowerVector":"-271.8409118652344, 1.1850886344909668, -395.38714599609375","Rotation":"0","TowerA1":"2305.2022417872213"},
{"TowerUpgraded":-271.8409118652344,"UpgradeCost":0,"UpgradePath":1},
{"TowerUpgraded":-271.8409118652344,"UpgradeCost":0,"UpgradePath":1},
{"TowerUpgraded":-271.8409118652344,"UpgradeCost":0,"UpgradePath":2},
{"TowerUpgraded":-271.8409118652344,"UpgradeCost":0,"UpgradePath":2},
{"TowerUpgraded":-271.8409118652344,"UpgradeCost":0,"UpgradePath":2},
{"TowerUpgraded":-271.8409118652344,"UpgradeCost":0,"UpgradePath":2},
{"TowerUpgraded":-271.8409118652344,"UpgradeCost":0,"UpgradePath":2},
{"TowerPlaceCost":325,"TowerPlaced":"Slammer","TowerVector":"-241.97564697265625, 1.1828293800354004, -401.3778076171875","Rotation":"0","TowerA1":"2313.367718697991"},
{"TowerUpgraded":-241.97564697265626,"UpgradeCost":0,"UpgradePath":1},
{"TowerUpgraded":-241.97564697265626,"UpgradeCost":0,"UpgradePath":1},
{"TowerUpgraded":-241.97564697265626,"UpgradeCost":0,"UpgradePath":1},
{"TowerUpgraded":-241.97564697265626,"UpgradeCost":0,"UpgradePath":1},
{"TowerUpgraded":-241.97564697265626,"UpgradeCost":0,"UpgradePath":1},
{"TowerUpgraded":-241.97564697265626,"UpgradeCost":0,"UpgradePath":2},
{"TowerUpgraded":-241.97564697265626,"UpgradeCost":0,"UpgradePath":2},
{"TowerPlaceCost":325,"TowerPlaced":"Slammer","TowerVector":"-252.13592529296875, 1.1828293800354004, -394.0765075683594","Rotation":"0","TowerA1":"2319.032152564265"},
{"TowerUpgraded":-252.13592529296876,"UpgradeCost":0,"UpgradePath":1},
{"TowerUpgraded":-252.13592529296876,"UpgradeCost":0,"UpgradePath":1},
{"TowerUpgraded":-252.13592529296876,"UpgradeCost":0,"UpgradePath":1},
{"TowerUpgraded":-252.13592529296876,"UpgradeCost":0,"UpgradePath":1},
{"TowerUpgraded":-252.13592529296876,"UpgradeCost":0,"UpgradePath":1},
{"TowerUpgraded":-252.13592529296876,"UpgradeCost":0,"UpgradePath":2},
{"TowerUpgraded":-252.13592529296876,"UpgradeCost":0,"UpgradePath":2},
{"TowerPlaceCost":325,"TowerPlaced":"Slammer","TowerVector":"-260.78033447265625, 1.0020931959152222, -393.96954345703125","Rotation":"0","TowerA1":"2323.9136488023214"},
{"TowerUpgraded":-260.78033447265627,"UpgradeCost":0,"UpgradePath":1},
{"TowerUpgraded":-260.78033447265627,"UpgradeCost":0,"UpgradePath":1},
{"TowerUpgraded":-260.78033447265627,"UpgradeCost":0,"UpgradePath":1},
{"TowerUpgraded":-260.78033447265627,"UpgradeCost":0,"UpgradePath":1},
{"TowerUpgraded":-260.78033447265627,"UpgradeCost":0,"UpgradePath":1},
{"TowerUpgraded":-260.78033447265627,"UpgradeCost":0,"UpgradePath":2},
{"TowerUpgraded":-260.78033447265627,"UpgradeCost":0,"UpgradePath":2},
{"TowerPlaceCost":900,"TowerPlaced":"Golden Ranger","TowerVector":"-257.703857421875, 1.0020922422409058, -393.82354736328125","Rotation":"0","TowerA1":"2329.4988328730687"},
{"TowerUpgraded":-257.703857421875,"UpgradeCost":0,"UpgradePath":2},
{"TowerUpgraded":-257.703857421875,"UpgradeCost":0,"UpgradePath":2},
{"TowerUpgraded":-257.703857421875,"UpgradeCost":0,"UpgradePath":2},
{"TowerUpgraded":-257.703857421875,"UpgradeCost":0,"UpgradePath":2},
{"TowerUpgraded":-257.703857421875,"UpgradeCost":0,"UpgradePath":1},
{"TowerUpgraded":-257.703857421875,"UpgradeCost":0,"UpgradePath":1},
{"TowerUpgraded":-257.703857421875,"UpgradeCost":0,"UpgradePath":2},
{"TowerPlaceCost":325,"TowerPlaced":"Slammer","TowerVector":"-234.29185485839844, 1.1850900650024414, -400.6366271972656","Rotation":"0","TowerA1":"2368.1224672682583"},
{"TowerUpgraded":-234.29185485839845,"UpgradeCost":0,"UpgradePath":1},
{"TowerUpgraded":-234.29185485839845,"UpgradeCost":0,"UpgradePath":1},
{"TowerUpgraded":-234.29185485839845,"UpgradeCost":0,"UpgradePath":1},
{"TowerUpgraded":-234.29185485839845,"UpgradeCost":0,"UpgradePath":1},
{"TowerUpgraded":-234.29185485839845,"UpgradeCost":0,"UpgradePath":1},
{"TowerUpgraded":-234.29185485839845,"UpgradeCost":0,"UpgradePath":2},
{"TowerUpgraded":-234.29185485839845,"UpgradeCost":0,"UpgradePath":2},
{"TowerPlaceCost":325,"TowerPlaced":"Slammer","TowerVector":"-231.21897888183594, 1.1850900650024414, -400.38946533203125","Rotation":"0","TowerA1":"2372.1530951941386"},
{"TowerUpgraded":-231.21897888183595,"UpgradeCost":0,"UpgradePath":1},
{"TowerUpgraded":-231.21897888183595,"UpgradeCost":0,"UpgradePath":1},
{"TowerUpgraded":-231.21897888183595,"UpgradeCost":0,"UpgradePath":1},
{"TowerUpgraded":-231.21897888183595,"UpgradeCost":0,"UpgradePath":1},
{"TowerUpgraded":-231.21897888183595,"UpgradeCost":0,"UpgradePath":1},
{"TowerUpgraded":-231.21897888183595,"UpgradeCost":0,"UpgradePath":2},
{"TowerUpgraded":-231.21897888183595,"UpgradeCost":0,"UpgradePath":2},
{"TowerPlaceCost":925,"TowerPlaced":"Toxicnator","TowerVector":"-233.58836364746094, 1.1850900650024414, -397.55279541015625","Rotation":"0","TowerA1":"2375.1241011428647"},
{"TowerUpgraded":-233.58836364746095,"UpgradeCost":0,"UpgradePath":2},
{"TowerUpgraded":-233.58836364746095,"UpgradeCost":0,"UpgradePath":2},
{"TowerUpgraded":-233.58836364746095,"UpgradeCost":0,"UpgradePath":2},
{"TowerUpgraded":-233.58836364746095,"UpgradeCost":0,"UpgradePath":2},
{"TowerUpgraded":-233.58836364746095,"UpgradeCost":0,"UpgradePath":2},
{"TowerUpgraded":-233.58836364746095,"UpgradeCost":0,"UpgradePath":1},
{"TowerUpgraded":-233.58836364746095,"UpgradeCost":0,"UpgradePath":1},
{"TowerPlaceCost":925,"TowerPlaced":"Toxicnator","TowerVector":"-230.56800842285156, 1.1850900650024414, -397.36529541015625","Rotation":"0","TowerA1":"2381.6761428993195"},
{"TowerUpgraded":-230.56800842285157,"UpgradeCost":0,"UpgradePath":2},
{"TowerUpgraded":-230.56800842285157,"UpgradeCost":0,"UpgradePath":2},
{"TowerUpgraded":-230.56800842285157,"UpgradeCost":0,"UpgradePath":2},
{"TowerUpgraded":-230.56800842285157,"UpgradeCost":0,"UpgradePath":2},
{"TowerUpgraded":-230.56800842285157,"UpgradeCost":0,"UpgradePath":2},
{"TowerUpgraded":-230.56800842285157,"UpgradeCost":0,"UpgradePath":1},
{"TowerUpgraded":-230.56800842285157,"UpgradeCost":0,"UpgradePath":1},
{"TowerPlaceCost":900,"TowerPlaced":"Golden Ranger","TowerVector":"-234.0322723388672, 1.1850900650024414, -394.42559814453125","Rotation":"0","TowerA1":"2385.914075470064"},
{"TowerUpgraded":-234.0322723388672,"UpgradeCost":0,"UpgradePath":2},
{"TowerUpgraded":-234.0322723388672,"UpgradeCost":0,"UpgradePath":2},
{"TowerUpgraded":-234.0322723388672,"UpgradeCost":0,"UpgradePath":2},
{"TowerUpgraded":-234.0322723388672,"UpgradeCost":0,"UpgradePath":2},
{"TowerUpgraded":-234.0322723388672,"UpgradeCost":0,"UpgradePath":2},
{"TowerUpgraded":-234.0322723388672,"UpgradeCost":0,"UpgradePath":1},
{"TowerUpgraded":-234.0322723388672,"UpgradeCost":0,"UpgradePath":1},
{"TowerPlaceCost":900,"TowerPlaced":"Golden Ranger","TowerVector":"-230.7652130126953, 1.1850900650024414, -394.33935546875","Rotation":"0","TowerA1":"2392.891651577316"},
{"TowerUpgraded":-230.7652130126953,"UpgradeCost":0,"UpgradePath":2},
{"TowerUpgraded":-230.7652130126953,"UpgradeCost":0,"UpgradePath":2},
{"TowerUpgraded":-230.7652130126953,"UpgradeCost":0,"UpgradePath":2},
{"TowerUpgraded":-230.7652130126953,"UpgradeCost":0,"UpgradePath":2},
{"TowerUpgraded":-230.7652130126953,"UpgradeCost":0,"UpgradePath":2},
{"TowerUpgraded":-230.7652130126953,"UpgradeCost":0,"UpgradePath":1},
{"TowerUpgraded":-230.7652130126953,"UpgradeCost":0,"UpgradePath":1},
{"TowerPlaceCost":325,"TowerPlaced":"Slammer","TowerVector":"-220.00759887695312, 1.1850900650024414, -401.4922790527344","Rotation":"0","TowerA1":"2416.613850797992"},
{"TowerUpgraded":-220.00759887695313,"UpgradeCost":0,"UpgradePath":1},
{"TowerUpgraded":-220.00759887695313,"UpgradeCost":0,"UpgradePath":1},
{"TowerUpgraded":-220.00759887695313,"UpgradeCost":0,"UpgradePath":1},
{"TowerUpgraded":-220.00759887695313,"UpgradeCost":0,"UpgradePath":1},
{"TowerUpgraded":-220.00759887695313,"UpgradeCost":0,"UpgradePath":1},
{"TowerUpgraded":-220.00759887695313,"UpgradeCost":0,"UpgradePath":2},
{"TowerUpgraded":-220.00759887695313,"UpgradeCost":0,"UpgradePath":2},
{"TowerPlaceCost":325,"TowerPlaced":"Slammer","TowerVector":"-223.0618438720703, 1.1850895881652832, -401.28338623046875","Rotation":"0","TowerA1":"2420.8811399019323"},
{"TowerUpgraded":-223.0618438720703,"UpgradeCost":0,"UpgradePath":1},
{"TowerUpgraded":-223.0618438720703,"UpgradeCost":0,"UpgradePath":1},
{"TowerUpgraded":-223.0618438720703,"UpgradeCost":0,"UpgradePath":1},
{"TowerUpgraded":-223.0618438720703,"UpgradeCost":0,"UpgradePath":1},
{"TowerUpgraded":-223.0618438720703,"UpgradeCost":0,"UpgradePath":1},
{"TowerUpgraded":-223.0618438720703,"UpgradeCost":0,"UpgradePath":2},
{"TowerUpgraded":-223.0618438720703,"UpgradeCost":0,"UpgradePath":2},
{"TowerPlaceCost":900,"TowerPlaced":"Golden Ranger","TowerVector":"-219.14306640625, 1.1828293800354004, -393.62109375","Rotation":"0","TowerA1":"2427.661590929143"},
{"TowerUpgraded":-219.14306640625,"UpgradeCost":0,"UpgradePath":2},
{"TowerUpgraded":-219.14306640625,"UpgradeCost":0,"UpgradePath":2},
{"TowerUpgraded":-219.14306640625,"UpgradeCost":0,"UpgradePath":2},
{"TowerUpgraded":-219.14306640625,"UpgradeCost":0,"UpgradePath":2},
{"TowerUpgraded":-219.14306640625,"UpgradeCost":0,"UpgradePath":2},
{"TowerUpgraded":-219.14306640625,"UpgradeCost":0,"UpgradePath":1},
{"TowerUpgraded":-219.14306640625,"UpgradeCost":0,"UpgradePath":1},
{"TowerPlaceCost":925,"TowerPlaced":"Toxicnator","TowerVector":"-216.04318237304688, 1.1828293800354004, -393.71832275390625","Rotation":"0","TowerA1":"2443.802506714128"},
{"TowerUpgraded":-216.04318237304688,"UpgradeCost":0,"UpgradePath":2},
{"TowerUpgraded":-216.04318237304688,"UpgradeCost":0,"UpgradePath":2},
{"TowerUpgraded":-216.04318237304688,"UpgradeCost":0,"UpgradePath":2},
{"TowerUpgraded":-216.04318237304688,"UpgradeCost":0,"UpgradePath":2},
{"TowerUpgraded":-216.04318237304688,"UpgradeCost":0,"UpgradePath":2},
{"TowerUpgraded":-216.04318237304688,"UpgradeCost":0,"UpgradePath":1},
{"TowerUpgraded":-216.04318237304688,"UpgradeCost":0,"UpgradePath":1},
{"TowerPlaceCost":325,"TowerPlaced":"Slammer","TowerVector":"-194.783447265625, 1.1850895881652832, -400.8600158691406","Rotation":"0","TowerA1":"2448.934669819195"},
{"TowerUpgraded":-194.783447265625,"UpgradeCost":0,"UpgradePath":1},
{"TowerUpgraded":-194.783447265625,"UpgradeCost":0,"UpgradePath":1},
{"TowerUpgraded":-194.783447265625,"UpgradeCost":0,"UpgradePath":1},
{"TowerUpgraded":-194.783447265625,"UpgradeCost":0,"UpgradePath":1},
{"TowerUpgraded":-194.783447265625,"UpgradeCost":0,"UpgradePath":1},
{"TowerUpgraded":-194.783447265625,"UpgradeCost":0,"UpgradePath":2},
{"TowerUpgraded":-194.783447265625,"UpgradeCost":0,"UpgradePath":2},
{"TowerPlaceCost":325,"TowerPlaced":"Slammer","TowerVector":"-205.465576171875, 1.185089111328125, -400.683349609375","Rotation":"0","TowerA1":"2453.523337243125"},
{"TowerUpgraded":-205.465576171875,"UpgradeCost":0,"UpgradePath":1},
{"TowerUpgraded":-205.465576171875,"UpgradeCost":0,"UpgradePath":1},
{"TowerUpgraded":-205.465576171875,"UpgradeCost":0,"UpgradePath":1},
{"TowerUpgraded":-205.465576171875,"UpgradeCost":0,"UpgradePath":1},
{"TowerUpgraded":-205.465576171875,"UpgradeCost":0,"UpgradePath":1},
{"TowerUpgraded":-205.465576171875,"UpgradeCost":0,"UpgradePath":2},
{"TowerUpgraded":-205.465576171875,"UpgradeCost":0,"UpgradePath":2},
{"TowerPlaceCost":325,"TowerPlaced":"Slammer","TowerVector":"-171.88128662109375, 1.185089111328125, -400.6969909667969","Rotation":"0","TowerA1":"2459.59744099807"},
{"TowerUpgraded":-171.88128662109376,"UpgradeCost":0,"UpgradePath":1},
{"TowerUpgraded":-171.88128662109376,"UpgradeCost":0,"UpgradePath":1},
{"TowerUpgraded":-171.88128662109376,"UpgradeCost":0,"UpgradePath":1},
{"TowerUpgraded":-171.88128662109376,"UpgradeCost":0,"UpgradePath":1},
{"TowerUpgraded":-171.88128662109376,"UpgradeCost":0,"UpgradePath":1},
{"TowerUpgraded":-171.88128662109376,"UpgradeCost":0,"UpgradePath":2},
{"TowerUpgraded":-171.88128662109376,"UpgradeCost":0,"UpgradePath":2},
{"TowerPlaceCost":325,"TowerPlaced":"Slammer","TowerVector":"-180.85693359375, 1.185089111328125, -400.6888732910156","Rotation":"0","TowerA1":"2463.3860034178942"},
{"TowerUpgraded":-180.85693359375,"UpgradeCost":0,"UpgradePath":1},
{"TowerUpgraded":-180.85693359375,"UpgradeCost":0,"UpgradePath":1},
{"TowerUpgraded":-180.85693359375,"UpgradeCost":0,"UpgradePath":1},
{"TowerUpgraded":-180.85693359375,"UpgradeCost":0,"UpgradePath":1},
{"TowerUpgraded":-180.85693359375,"UpgradeCost":0,"UpgradePath":1},
{"TowerUpgraded":-180.85693359375,"UpgradeCost":0,"UpgradePath":2},
{"TowerUpgraded":-180.85693359375,"UpgradeCost":0,"UpgradePath":2},
{"TowerPlaceCost":900,"TowerPlaced":"Golden Ranger","TowerVector":"-189.01486206054688, 1.185089111328125, -400.59521484375","Rotation":"0","TowerA1":"2469.8204548619688"},
{"TowerUpgraded":-189.01486206054688,"UpgradeCost":0,"UpgradePath":1},
{"TowerUpgraded":-189.01486206054688,"UpgradeCost":0,"UpgradePath":1},
{"TowerUpgraded":-189.01486206054688,"UpgradeCost":0,"UpgradePath":2},
{"TowerUpgraded":-189.01486206054688,"UpgradeCost":0,"UpgradePath":2},
{"TowerUpgraded":-189.01486206054688,"UpgradeCost":0,"UpgradePath":2},
{"TowerUpgraded":-189.01486206054688,"UpgradeCost":0,"UpgradePath":2},
{"TowerUpgraded":-189.01486206054688,"UpgradeCost":0,"UpgradePath":2},
{"TowerPlaceCost":900,"TowerPlaced":"Golden Ranger","TowerVector":"-172.05014038085938, 1.1057276725769043, -408.4061584472656","Rotation":"0","TowerA1":"2475.0704541779123"},
{"TowerUpgraded":-172.05014038085938,"UpgradeCost":0,"UpgradePath":2},
{"TowerUpgraded":-172.05014038085938,"UpgradeCost":0,"UpgradePath":2},
{"TowerUpgraded":-172.05014038085938,"UpgradeCost":0,"UpgradePath":2},
{"TowerUpgraded":-172.05014038085938,"UpgradeCost":0,"UpgradePath":2},
{"TowerUpgraded":-172.05014038085938,"UpgradeCost":0,"UpgradePath":2},
{"TowerUpgraded":-172.05014038085938,"UpgradeCost":0,"UpgradePath":1},
{"TowerUpgraded":-172.05014038085938,"UpgradeCost":0,"UpgradePath":1},
{"TowerPlaceCost":900,"TowerPlaced":"Golden Ranger","TowerVector":"-205.84288024902344, 1.185089111328125, -408.2511291503906","Rotation":"0","TowerA1":"2479.7061885949224"},
{"TowerUpgraded":-205.84288024902345,"UpgradeCost":0,"UpgradePath":2},
{"TowerUpgraded":-205.84288024902345,"UpgradeCost":0,"UpgradePath":2},
{"TowerUpgraded":-205.84288024902345,"UpgradeCost":0,"UpgradePath":2},
{"TowerUpgraded":-205.84288024902345,"UpgradeCost":0,"UpgradePath":2},
{"TowerUpgraded":-205.84288024902345,"UpgradeCost":0,"UpgradePath":2},
{"TowerUpgraded":-205.84288024902345,"UpgradeCost":0,"UpgradePath":1},
{"TowerUpgraded":-205.84288024902345,"UpgradeCost":0,"UpgradePath":1},
{"TowerPlaceCost":925,"TowerPlaced":"Toxicnator","TowerVector":"-199.9882354736328, 1.1850895881652832, -408.2289733886719","Rotation":"0","TowerA1":"2483.51717864722"},
{"TowerUpgraded":-199.9882354736328,"UpgradeCost":0,"UpgradePath":2},
{"TowerUpgraded":-199.9882354736328,"UpgradeCost":0,"UpgradePath":2},
{"TowerUpgraded":-199.9882354736328,"UpgradeCost":0,"UpgradePath":2},
{"TowerUpgraded":-199.9882354736328,"UpgradeCost":0,"UpgradePath":2},
{"TowerUpgraded":-199.9882354736328,"UpgradeCost":0,"UpgradePath":2},
{"TowerUpgraded":-199.9882354736328,"UpgradeCost":0,"UpgradePath":1},
{"TowerUpgraded":-199.9882354736328,"UpgradeCost":0,"UpgradePath":1},
{"TowerPlaceCost":925,"TowerPlaced":"Toxicnator","TowerVector":"-183.49179077148438, 1.185089111328125, -408.1011962890625","Rotation":"0","TowerA1":"2488.909476779867"},
{"TowerUpgraded":-183.49179077148438,"UpgradeCost":0,"UpgradePath":2},
{"TowerUpgraded":-183.49179077148438,"UpgradeCost":0,"UpgradePath":2},
{"TowerUpgraded":-183.49179077148438,"UpgradeCost":0,"UpgradePath":2},
{"TowerUpgraded":-183.49179077148438,"UpgradeCost":0,"UpgradePath":2},
{"TowerUpgraded":-183.49179077148438,"UpgradeCost":0,"UpgradePath":2},
{"TowerUpgraded":-183.49179077148438,"UpgradeCost":0,"UpgradePath":1},
{"TowerUpgraded":-183.49179077148438,"UpgradeCost":0,"UpgradePath":1},
{"TowerPlaceCost":325,"TowerPlaced":"Slammer","TowerVector":"-166.39466857910156, 1.8321521282196045, -408.7749938964844","Rotation":"0","TowerA1":"2495.150020837318"},
{"TowerUpgraded":-166.39466857910157,"UpgradeCost":0,"UpgradePath":1},
{"TowerUpgraded":-166.39466857910157,"UpgradeCost":0,"UpgradePath":1},
{"TowerUpgraded":-166.39466857910157,"UpgradeCost":0,"UpgradePath":1},
{"TowerUpgraded":-166.39466857910157,"UpgradeCost":0,"UpgradePath":1},
{"TowerUpgraded":-166.39466857910157,"UpgradeCost":0,"UpgradePath":1},
{"TowerUpgraded":-166.39466857910157,"UpgradeCost":0,"UpgradePath":2},
{"TowerUpgraded":-166.39466857910157,"UpgradeCost":0,"UpgradePath":2},
{"TowerPlaceCost":325,"TowerPlaced":"Slammer","TowerVector":"-162.44598388671875, 2.9450535774230957, -408.1857604980469","Rotation":"0","TowerA1":"2499.3651964962482"},
{"TowerUpgraded":-162.44598388671876,"UpgradeCost":0,"UpgradePath":2},
{"TowerUpgraded":-162.44598388671876,"UpgradeCost":0,"UpgradePath":1},
{"TowerUpgraded":-162.44598388671876,"UpgradeCost":0,"UpgradePath":1},
{"TowerUpgraded":-162.44598388671876,"UpgradeCost":0,"UpgradePath":1},
{"TowerUpgraded":-162.44598388671876,"UpgradeCost":0,"UpgradePath":1},
{"TowerUpgraded":-162.44598388671876,"UpgradeCost":0,"UpgradePath":1},
{"TowerUpgraded":-162.44598388671876,"UpgradeCost":0,"UpgradePath":2},
{"TowerPlaceCost":325,"TowerPlaced":"Slammer","TowerVector":"-162.6862030029297, 2.9450621604919434, -400.7198181152344","Rotation":"0","TowerA1":"2506.1605576789007"},
{"TowerUpgraded":-162.6862030029297,"UpgradeCost":0,"UpgradePath":1},
{"TowerUpgraded":-162.6862030029297,"UpgradeCost":0,"UpgradePath":1},
{"TowerUpgraded":-162.6862030029297,"UpgradeCost":0,"UpgradePath":1},
{"TowerUpgraded":-162.6862030029297,"UpgradeCost":0,"UpgradePath":1},
{"TowerUpgraded":-162.6862030029297,"UpgradeCost":0,"UpgradePath":1},
{"TowerUpgraded":-162.6862030029297,"UpgradeCost":0,"UpgradePath":2},
{"TowerUpgraded":-162.6862030029297,"UpgradeCost":0,"UpgradePath":2},
{"TowerPlaceCost":325,"TowerPlaced":"Slammer","TowerVector":"-158.14602661132812, 3.7796385288238525, -400.7937316894531","Rotation":"0","TowerA1":"2509.4301686962135"},
{"TowerUpgraded":-158.14602661132813,"UpgradeCost":0,"UpgradePath":1},
{"TowerUpgraded":-158.14602661132813,"UpgradeCost":0,"UpgradePath":1},
{"TowerUpgraded":-158.14602661132813,"UpgradeCost":0,"UpgradePath":1},
{"TowerUpgraded":-158.14602661132813,"UpgradeCost":0,"UpgradePath":1},
{"TowerUpgraded":-158.14602661132813,"UpgradeCost":0,"UpgradePath":1},
{"TowerUpgraded":-158.14602661132813,"UpgradeCost":0,"UpgradePath":2},
{"TowerUpgraded":-158.14602661132813,"UpgradeCost":0,"UpgradePath":2},
{"TowerPlaceCost":925,"TowerPlaced":"Toxicnator","TowerVector":"-159.81182861328125, 3.7794928550720215, -397.4983825683594","Rotation":"0","TowerA1":"2514.968697351869"},
{"TowerUpgraded":-159.81182861328126,"UpgradeCost":0,"UpgradePath":2},
{"TowerUpgraded":-159.81182861328126,"UpgradeCost":0,"UpgradePath":2},
{"TowerUpgraded":-159.81182861328126,"UpgradeCost":0,"UpgradePath":2},
{"TowerUpgraded":-159.81182861328126,"UpgradeCost":0,"UpgradePath":2},
{"TowerUpgraded":-159.81182861328126,"UpgradeCost":0,"UpgradePath":1},
{"TowerUpgraded":-159.81182861328126,"UpgradeCost":0,"UpgradePath":1},
{"TowerUpgraded":-159.81182861328126,"UpgradeCost":0,"UpgradePath":2},
{"TowerPlaceCost":900,"TowerPlaced":"Golden Ranger","TowerVector":"-154.1487579345703, 4.915287971496582, -409.0230712890625","Rotation":"0","TowerA1":"2527.1872669300064"},
{"TowerUpgraded":-154.1487579345703,"UpgradeCost":0,"UpgradePath":2},
{"TowerUpgraded":-154.1487579345703,"UpgradeCost":0,"UpgradePath":2},
{"TowerUpgraded":-154.1487579345703,"UpgradeCost":0,"UpgradePath":2},
{"TowerUpgraded":-154.1487579345703,"UpgradeCost":0,"UpgradePath":2},
{"TowerUpgraded":-154.1487579345703,"UpgradeCost":0,"UpgradePath":2},
{"TowerUpgraded":-154.1487579345703,"UpgradeCost":0,"UpgradePath":1},
{"TowerUpgraded":-154.1487579345703,"UpgradeCost":0,"UpgradePath":1},
{"TowerPlaceCost":225,"TowerPlaced":"Cryo Blaster","TowerVector":"-241.89161682128906, 1.1828293800354004, -405.44189453125","Rotation":"0","TowerA1":"2561.4797181412578"},
{"TowerUpgraded":-241.89161682128907,"UpgradeCost":0,"UpgradePath":2},
{"TowerUpgraded":-241.89161682128907,"UpgradeCost":0,"UpgradePath":2},
{"TowerUpgraded":-241.89161682128907,"UpgradeCost":0,"UpgradePath":2},
{"TowerUpgraded":-241.89161682128907,"UpgradeCost":0,"UpgradePath":2},
{"TowerUpgraded":-241.89161682128907,"UpgradeCost":0,"UpgradePath":2},
{"TowerUpgraded":-241.89161682128907,"UpgradeCost":0,"UpgradePath":1},
{"TowerUpgraded":-241.89161682128907,"UpgradeCost":0,"UpgradePath":1},
{"TowerPlaceCost":225,"TowerPlaced":"Cryo Blaster","TowerVector":"-243.37484741210938, 1.1828293800354004, -408.3008728027344","Rotation":"0","TowerA1":"2565.564193517901"},
{"TowerUpgraded":-243.37484741210938,"UpgradeCost":0,"UpgradePath":2},
{"TowerUpgraded":-243.37484741210938,"UpgradeCost":0,"UpgradePath":2},
{"TowerUpgraded":-243.37484741210938,"UpgradeCost":0,"UpgradePath":2},
{"TowerUpgraded":-243.37484741210938,"UpgradeCost":0,"UpgradePath":2},
{"TowerUpgraded":-243.37484741210938,"UpgradeCost":0,"UpgradePath":2},
{"TowerUpgraded":-243.37484741210938,"UpgradeCost":0,"UpgradePath":1},
{"TowerUpgraded":-243.37484741210938,"UpgradeCost":0,"UpgradePath":1},
{"TowerPlaceCost":925,"TowerPlaced":"Toxicnator","TowerVector":"-248.54806518554688, 1.1828293800354004, -393.4488220214844","Rotation":"0","TowerA1":"2595.3842609692365"},
{"TowerUpgraded":-248.54806518554688,"UpgradeCost":0,"UpgradePath":2},
{"TowerUpgraded":-248.54806518554688,"UpgradeCost":0,"UpgradePath":2},
{"TowerUpgraded":-248.54806518554688,"UpgradeCost":0,"UpgradePath":2},
{"TowerUpgraded":-248.54806518554688,"UpgradeCost":0,"UpgradePath":2},
{"TowerUpgraded":-248.54806518554688,"UpgradeCost":0,"UpgradePath":2},
{"TowerUpgraded":-248.54806518554688,"UpgradeCost":0,"UpgradePath":1},
{"TowerUpgraded":-248.54806518554688,"UpgradeCost":0,"UpgradePath":1}
]
